{"schema":1,"kind":"bidding","id":"ben1-00011354","created_at":"2026-07-18T07:22:08+00:00","generator":{"engine":"ben BEN-21GF","seed":70484,"samples":512,"oracle":"none","elapsed_s":21.9},"scoring_form":"IMPs","dealer":"S","vul":"None","seat":"W","hand":"J9.K98.KJ.AQJ943","auction":["P","1NT","P","2C","P","2D","P","2NT","P"],"candidates":[{"call":"4C","policy":0.524},{"call":"3C","policy":0.442},{"call":"P","policy":0.211}],"verdict":{"accepted":"P","toss_up":false,"toss_up_set":[],"flags":[],"table":[{"bid":"3C","ev_imp_vs_top":0.31,"vs":"P","ci":0.35,"p_gain":0.375,"p_loss":0.527,"p_push":0.098,"best_share":0.332,"top_contracts":[["3NW",334],["3CE",153],["4CE",19]]},{"bid":"P","ev_imp_vs_top":-0.31,"vs":"3C","ci":0.35,"p_gain":0.527,"p_loss":0.375,"p_push":0.098,"best_share":0.326,"top_contracts":[["2NW",512]]},{"bid":"4C","ev_imp_vs_top":-1.91,"vs":"3C","ci":0.36,"p_gain":0.234,"p_loss":0.5,"p_push":0.266,"best_share":0.1,"top_contracts":[["4CE",485],["5CE",27]]}],"dead_options":[]},"difficulty":0.31,"quality":{"n_samples":512,"quality":0.88,"gap_imps":0.31,"ci":0.35,"stakes":3.55,"doubled_share":0.0,"top2":["3C","P"],"q":0.902,"p4":0.537,"tv":1.0,"flip":0.0,"span":true,"trap":false,"damage":false,"interest":80,"p_top_wins":0.375,"p_second_wins":0.527,"winner_by":"win-rate over a sub-0.5-IMP EV edge","half_stats":[{"gap_imps":-0.21,"p_top_wins":0.312,"p_second_wins":0.562},{"gap_imps":0.84,"p_top_wins":0.438,"p_second_wins":0.492}]},"explanations":{"note":"call meanings follow standard 2/1 Game Force","stem":[{"idx":0,"seat":"S","call":"P","card":{"text":"","hcp":[0,11],"minlen":{"C":0,"D":0,"H":0,"S":0}},"text":"Pass (S): 0-11"},{"idx":1,"seat":"W","call":"1NT","card":{"text":"NT style","hcp":[15,17],"minlen":{"C":2,"D":2,"H":2,"S":2}},"text":"1NT (W): NT style, 15-17"},{"idx":2,"seat":"N","call":"P","card":{"text":"","hcp":[0,17],"minlen":{"C":0,"D":0,"H":0,"S":0}},"text":"Pass (N): 0-17"},{"idx":3,"seat":"E","call":"2C","card":{"text":"Stayman","hcp":[7,37],"minlen":{"C":0,"D":0,"H":0,"S":0}},"text":"2\u2663 (E): Stayman, 7+"},{"idx":4,"seat":"S","call":"P","card":{"text":"","hcp":[0,11],"minlen":{"C":0,"D":0,"H":0,"S":0}},"text":"Pass (S): 0-11"},{"idx":5,"seat":"W","call":"2D","card":{"text":"no major suits","hcp":[15,17],"minlen":{"C":2,"D":2,"H":2,"S":2}},"text":"2\u2666 (W): no major suits, 15-17"},{"idx":6,"seat":"N","call":"P","card":{"text":"","hcp":[0,17],"minlen":{"C":0,"D":0,"H":0,"S":0}},"text":"Pass (N): 0-17"},{"idx":7,"seat":"E","call":"2NT","card":{"text":"calculated bid","hcp":[7,9],"minlen":{"C":2,"D":2,"H":2,"S":2}},"text":"2NT (E): 7-9"},{"idx":8,"seat":"S","call":"P","card":{"text":"","hcp":[0,11],"minlen":{"C":0,"D":0,"H":0,"S":0}},"text":"Pass (S): 0-11"}],"options":[{"bid":"3C","text":"3\u2663 \u2014 5+\u2663, 17-17. Leads to 3NT W 65%, 3\u2663E 30%, 4\u2663E 4%. Engine: 44%. +0.3 IMPs vs the top choice (\u00b10.3), wins 38%, pushes 10%.","card":{"text":"bidable suit","hcp":[17,17],"minlen":{"C":5,"D":2,"H":2,"S":2}}},{"bid":"P","text":"Pass \u2014 15-17. Leads to 2NT W 100%. Engine: 21%. Best: +0.3 IMPs vs 3\u2663 (\u00b10.3), wins 38% of layouts.","card":{"text":"","hcp":[15,17],"minlen":{"C":2,"D":2,"H":2,"S":2}}},{"bid":"4C","text":"4\u2663 \u2014 6+\u2663, 15-17. Leads to 4\u2663E 95%, 5\u2663E 5%. Engine: 52%. -1.9 IMPs vs the top choice (\u00b10.4), wins 23%, pushes 27%.","card":{"text":"bidable suit","hcp":[15,17],"minlen":{"C":6,"D":2,"H":2,"S":2}}}]},"hero_role":"opener","full_deal":{"N":"AK82.542.Q43.KT8","E":"Q74.QJ63.A762.65","S":"T653.AT7.T985.72","W":"J9.K98.KJ.AQJ943"},"engine_auction_complete":["P","1NT","P","2C","P","2D","P","2NT","P","4C","P","P","P"],"policy_trail":[{"idx":0,"seat":"S","chosen":"P","policy":[["P",1.2]]},{"idx":1,"seat":"W","chosen":"1NT","policy":[["1NT",1.164]]},{"idx":2,"seat":"N","chosen":"P","policy":[["P",1.199]]},{"idx":3,"seat":"E","chosen":"2C","policy":[["2C",1.198]]},{"idx":4,"seat":"S","chosen":"P","policy":[["P",1.2]]},{"idx":5,"seat":"W","chosen":"2D","policy":[["2D",1.2]]},{"idx":6,"seat":"N","chosen":"P","policy":[["P",1.198]]},{"idx":7,"seat":"E","chosen":"2NT","policy":[["2NT",0.595],["3NT",0.545]]},{"idx":8,"seat":"S","chosen":"P","policy":[["P",1.2]]},{"idx":9,"seat":"W","chosen":"4C","policy":[["4C",0.524],["3C",0.442],["P",0.211]]},{"idx":10,"seat":"N","chosen":"P","policy":[["P",1.2]]},{"idx":11,"seat":"E","chosen":"P","policy":[["P",0.958],["4D",0.083]]},{"idx":12,"seat":"S","chosen":"P","policy":[["P",1.2]]}],"classification":{"difficulty_score":74.2,"difficulty_level":5,"type":"invite_or_game","type_reason":"With a running club suit and 15-17, West must decide whether to bid game (4C), invite (3C), or settle for 2NT after East showed a minimum invitational hand."}}