{"schema":1,"kind":"bidding","id":"ben1-00011a3e","created_at":"2026-07-18T07:50:41+00:00","generator":{"engine":"ben BEN-21GF","seed":72254,"samples":512,"oracle":"none","elapsed_s":18.9},"scoring_form":"IMPs","dealer":"W","vul":"EW","seat":"E","hand":"KJ84.K4.KJ.AJ986","auction":["2H","P","2NT","3D","P","P"],"candidates":[{"call":"4D","policy":0.423},{"call":"3H","policy":0.365},{"call":"4H","policy":0.287}],"verdict":{"accepted":"3H","toss_up":false,"toss_up_set":[],"flags":[],"table":[{"bid":"3H","ev_imp_vs_top":1.6,"vs":"4H","ci":0.6,"p_gain":0.627,"p_loss":0.246,"p_push":0.127,"best_share":0.613,"top_contracts":[["3HW",271],["4DS",79],["3HXW",63]]},{"bid":"4H","ev_imp_vs_top":-1.6,"vs":"3H","ci":0.6,"p_gain":0.246,"p_loss":0.627,"p_push":0.127,"best_share":0.029,"top_contracts":[["4HW",483],["4HXW",16],["4HXXW",7]]},{"bid":"4D","ev_imp_vs_top":-2.09,"vs":"3H","ci":0.61,"p_gain":0.229,"p_loss":0.648,"p_push":0.123,"best_share":0.014,"top_contracts":[["4HW",447],["6HW",20],["4HXW",14]]}],"dead_options":[]},"difficulty":1.6,"quality":{"n_samples":512,"quality":0.82,"gap_imps":1.6,"ci":0.6,"stakes":6.01,"doubled_share":0.3,"top2":["3H","4H"],"q":0.873,"p4":0.593,"tv":0.875,"flip":0.219,"span":true,"trap":true,"damage":false,"interest":100,"p_top_wins":0.627,"p_second_wins":0.246,"winner_by":"EV gap >= 0.5 IMPs","half_stats":[{"gap_imps":1.94,"p_top_wins":0.66,"p_second_wins":0.238},{"gap_imps":1.27,"p_top_wins":0.594,"p_second_wins":0.254}]},"explanations":{"note":"call meanings follow standard 2/1 Game Force","stem":[{"idx":0,"seat":"W","call":"2H","card":{"text":"Weak natural 2M","hcp":[6,10],"minlen":{"C":0,"D":0,"H":6,"S":0}},"text":"2\u2665 (W): Weak natural 2M, 6+\u2665, 6-10"},{"idx":1,"seat":"N","call":"P","card":{"text":"","hcp":[0,16],"minlen":{"C":0,"D":0,"H":0,"S":0}},"text":"Pass (N): 0-16"},{"idx":2,"seat":"E","call":"2NT","card":{"text":"Ogust","hcp":[12,37],"minlen":{"C":0,"D":0,"H":0,"S":0}},"text":"2NT (E): Ogust, 12+"},{"idx":3,"seat":"S","call":"3D","card":{"text":"bidable suit","hcp":[13,26],"minlen":{"C":0,"D":5,"H":0,"S":0}},"text":"3\u2666 (S): 5+\u2666, 13+"},{"idx":4,"seat":"W","call":"P","card":{"text":"","hcp":[6,10],"minlen":{"C":0,"D":0,"H":6,"S":0}},"text":"Pass (W): 6+\u2665, 6-10"},{"idx":5,"seat":"N","call":"P","card":{"text":"","hcp":[0,10],"minlen":{"C":0,"D":0,"H":0,"S":0}},"text":"Pass (N): 0-10"}],"options":[{"bid":"3H","text":"3\u2665 \u2014 12-15. Leads to 3\u2665W 53%, 4\u2666S 15%, 3HXW 12%. Engine: 36%. Best: +1.6 IMPs vs 4\u2665 (\u00b10.6), wins 63% of layouts.","card":{"text":"calculated bid","hcp":[12,15],"minlen":{"C":0,"D":0,"H":2,"S":0}}},{"bid":"4H","text":"4\u2665 \u2014 15+. Leads to 4\u2665W 94%, 4HXW 3%, 4HXXW 1%. Engine: 29%. -1.6 IMPs vs the top choice (\u00b10.6), wins 25%, pushes 13%.","card":{"text":"calculated bid","hcp":[15,27],"minlen":{"C":0,"D":0,"H":2,"S":0}}},{"bid":"4D","text":"4\u2666 \u2014 15+. Leads to 4\u2665W 87%, 6\u2665W 4%, 4HXW 3%. Engine: 42%. -2.1 IMPs vs the top choice (\u00b10.6), wins 23%, pushes 12%.","card":{"text":"limit raise or better in !H","hcp":[15,37],"minlen":{"C":0,"D":0,"H":2,"S":0}}}]},"hero_role":"responder","full_deal":{"N":"QT97.Q532.T8764.","E":"KJ84.K4.KJ.AJ986","S":"A32.8.AQ952.K732","W":"65.AJT976.3.QT54"},"engine_auction_complete":["2H","P","2NT","3D","P","P","4D","P","4H","5D","X","P","P","P"],"policy_trail":[{"idx":0,"seat":"W","chosen":"2H","policy":[["2H",1.195]]},{"idx":1,"seat":"N","chosen":"P","policy":[["P",1.2]]},{"idx":2,"seat":"E","chosen":"2NT","policy":[["2NT",1.195]]},{"idx":3,"seat":"S","chosen":"3D","policy":[["3D",0.958],["P",0.211]]},{"idx":4,"seat":"W","chosen":"P","policy":[["P",1.013]]},{"idx":5,"seat":"N","chosen":"P","policy":[["P",0.565],["5D",0.473],["4D",0.145]]},{"idx":6,"seat":"E","chosen":"4D","policy":[["4D",0.423],["3H",0.365],["4H",0.287]]},{"idx":7,"seat":"S","chosen":"P","policy":[["P",1.114]]},{"idx":8,"seat":"W","chosen":"4H","policy":[["4H",1.098],["4S",0.05]]},{"idx":9,"seat":"N","chosen":"5D","policy":[["5D",0.793],["P",0.392]]},{"idx":10,"seat":"E","chosen":"X","policy":[["X",0.991],["P",0.151]]},{"idx":11,"seat":"S","chosen":"P","policy":[["P",1.194]]},{"idx":12,"seat":"W","chosen":"P","policy":[["P",1.148],["5H",0.043]]},{"idx":13,"seat":"N","chosen":"P","policy":[["P",1.186]]}],"classification":{"difficulty_score":52.2,"difficulty_level":3,"type":"choice_of_strain","type_reason":"Level/game is essentially decided (3D was 13+ forcing-ish, hand is strong); the choice is between 4D, 3H, 4H strain/level with hearts vs diamonds as the fit."}}