{"schema":1,"kind":"bidding","id":"ben1-00013f05","created_at":"2026-07-18T08:54:29+00:00","generator":{"engine":"ben BEN-21GF","seed":81669,"samples":299,"oracle":"none","elapsed_s":22.9},"scoring_form":"IMPs","dealer":"E","vul":"None","seat":"E","hand":"K7.KJT7653.7.K63","auction":["1H","P","1S","3C","P","P","3S","P"],"candidates":[{"call":"P","policy":0.392},{"call":"4H","policy":0.307},{"call":"4S","policy":0.289},{"call":"4C","policy":0.084}],"verdict":{"accepted":"4H","toss_up":false,"toss_up_set":[],"flags":[],"table":[{"bid":"4H","ev_imp_vs_top":2.02,"vs":"4S","ci":0.66,"p_gain":0.545,"p_loss":0.177,"p_push":0.278,"best_share":0.401,"top_contracts":[["4HE",263],["5HE",28],["4SW",4]]},{"bid":"4S","ev_imp_vs_top":-2.02,"vs":"4H","ci":0.66,"p_gain":0.177,"p_loss":0.545,"p_push":0.278,"best_share":0.054,"top_contracts":[["4SW",294],["4SXW",2],["5HE",1]]},{"bid":"P","ev_imp_vs_top":-2.05,"vs":"4H","ci":0.63,"p_gain":0.331,"p_loss":0.525,"p_push":0.144,"best_share":0.251,"top_contracts":[["3SW",298],["4SW",1]]},{"bid":"4C","ev_imp_vs_top":-3.93,"vs":"4H","ci":0.67,"p_gain":0.127,"p_loss":0.629,"p_push":0.244,"best_share":0.01,"top_contracts":[["4SW",185],["5SW",82],["6SW",19]]}],"dead_options":[]},"difficulty":2.02,"quality":{"n_samples":299,"quality":0.78,"gap_imps":2.02,"ci":0.66,"stakes":4.16,"doubled_share":0.03,"top2":["4H","4S"],"q":0.722,"p4":0.326,"tv":0.983,"flip":0.0,"span":false,"trap":true,"damage":false,"interest":85.4,"p_top_wins":0.545,"p_second_wins":0.177,"winner_by":"EV gap >= 0.5 IMPs","half_stats":[{"gap_imps":3.01,"p_top_wins":0.638,"p_second_wins":0.121},{"gap_imps":1.03,"p_top_wins":0.453,"p_second_wins":0.233}]},"explanations":{"note":"call meanings follow standard 2/1 Game Force","stem":[{"idx":0,"seat":"E","call":"1H","card":{"text":"5+ !H","hcp":[11,20],"minlen":{"C":0,"D":0,"H":5,"S":0}},"text":"1\u2665 (E): 5+\u2665, 11-20"},{"idx":1,"seat":"S","call":"P","card":{"text":"","hcp":[0,14],"minlen":{"C":0,"D":0,"H":0,"S":0}},"text":"Pass (S): 0-14"},{"idx":2,"seat":"W","call":"1S","card":{"text":"bidable suit","hcp":[6,29],"minlen":{"C":0,"D":0,"H":0,"S":4}},"text":"1\u2660 (W): 4+\u2660, 6+"},{"idx":3,"seat":"N","call":"3C","card":{"text":"preemptive","hcp":[2,12],"minlen":{"C":7,"D":0,"H":0,"S":0}},"text":"3\u2663 (N): preemptive, 7+\u2663, 2-12"},{"idx":4,"seat":"E","call":"P","card":{"text":"","hcp":[11,18],"minlen":{"C":0,"D":0,"H":5,"S":0}},"text":"Pass (E): 5+\u2665, 11-18"},{"idx":5,"seat":"S","call":"P","card":{"text":"","hcp":[0,14],"minlen":{"C":0,"D":0,"H":0,"S":0}},"text":"Pass (S): 0-14"},{"idx":6,"seat":"W","call":"3S","card":{"text":"bidable suit","hcp":[11,27],"minlen":{"C":0,"D":0,"H":0,"S":6}},"text":"3\u2660 (W): 6+\u2660, 11+"},{"idx":7,"seat":"N","call":"P","card":{"text":"","hcp":[2,12],"minlen":{"C":7,"D":0,"H":0,"S":0}},"text":"Pass (N): 7+\u2663, 2-12"}],"options":[{"bid":"4H","text":"4\u2665 \u2014 6+\u2665, 12-18. Leads to 4\u2665E 88%, 5\u2665E 9%, 4\u2660W 1%. Engine: 31%. Best: +2.0 IMPs vs 4\u2660 (\u00b10.7), wins 55% of layouts.","card":{"text":"bidable suit","hcp":[12,18],"minlen":{"C":0,"D":0,"H":6,"S":0}}},{"bid":"4S","text":"4\u2660 \u2014 5+\u2665, 11-18. Leads to 4\u2660W 98%, 4SXW 1%, 5\u2665E 0%. Engine: 29%. -2.0 IMPs vs the top choice (\u00b10.7), wins 18%, pushes 28%.","card":{"text":"calculated bid","hcp":[11,18],"minlen":{"C":0,"D":0,"H":5,"S":1}}},{"bid":"P","text":"Pass \u2014 5+\u2665, 11-13. Leads to 3\u2660W 100%, 4\u2660W 0%. Engine: 39%. -2.0 IMPs vs the top choice (\u00b10.6), wins 33%, pushes 14%.","card":{"text":"","hcp":[11,13],"minlen":{"C":0,"D":0,"H":5,"S":0}}},{"bid":"4C","text":"4\u2663 \u2014 5+\u2665, 14-18. Leads to 4\u2660W 62%, 5\u2660W 27%, 6\u2660W 6%. Engine: 8%. -3.9 IMPs vs the top choice (\u00b10.7), wins 13%, pushes 24%.","card":{"text":"limit raise or better in !S","hcp":[14,18],"minlen":{"C":0,"D":0,"H":5,"S":2}}}]},"hero_role":"opener","full_deal":{"N":"4.8.AJT4.AT97542","E":"K7.KJT7653.7.K63","S":"QJT9.Q942.K953.8","W":"A86532.A.Q862.QJ"},"engine_auction_complete":["1H","P","1S","3C","P","P","3S","P","P","P"],"policy_trail":[{"idx":0,"seat":"E","chosen":"1H","policy":[["1H",0.787],["3H",0.316]]},{"idx":1,"seat":"S","chosen":"P","policy":[["P",1.2]]},{"idx":2,"seat":"W","chosen":"1S","policy":[["1S",1.199]]},{"idx":3,"seat":"N","chosen":"3C","policy":[["3C",1.158]]},{"idx":4,"seat":"E","chosen":"P","policy":[["P",0.73],["3H",0.371],["4H",0.062]]},{"idx":5,"seat":"S","chosen":"P","policy":[["P",1.198]]},{"idx":6,"seat":"W","chosen":"3S","policy":[["3S",0.955],["4S",0.151]]},{"idx":7,"seat":"N","chosen":"P","policy":[["P",1.199]]},{"idx":8,"seat":"E","chosen":"P","policy":[["P",0.392],["4H",0.307],["4S",0.289],["4C",0.084]]},{"idx":9,"seat":"S","chosen":"P","policy":[["P",1.195]]}],"classification":{"difficulty_score":52.1,"difficulty_level":3,"type":"choice_of_strain","type_reason":"With the level essentially set (E is clearly bidding on with a strong 6-1-5-1 hand), the choice is between 4H and 4S/other strain, i.e. which suit to play in."}}