{"schema":1,"kind":"bidding","id":"ben1-0007aa89","created_at":"2026-07-18T23:26:34+00:00","generator":{"engine":"ben BEN-21GF","seed":502409,"samples":512,"oracle":"none","elapsed_s":21.3},"scoring_form":"IMPs","dealer":"N","vul":"NS","seat":"S","hand":"KJ9.T9873.53.AT9","auction":["1S","P","2S","3D","P","P"],"candidates":[{"call":"P","policy":0.592},{"call":"3S","policy":0.591}],"verdict":{"accepted":"3S","toss_up":false,"toss_up_set":[],"flags":[],"table":[{"bid":"3S","ev_imp_vs_top":1.39,"vs":"P","ci":0.37,"p_gain":0.629,"p_loss":0.236,"p_push":0.135,"best_share":0.693,"top_contracts":[["3SN",296],["4DW",105],["3SXN",34]]},{"bid":"P","ev_imp_vs_top":-1.39,"vs":"3S","ci":0.37,"p_gain":0.236,"p_loss":0.629,"p_push":0.135,"best_share":0.248,"top_contracts":[["3DW",512]]}],"dead_options":[]},"difficulty":1.39,"quality":{"n_samples":512,"quality":0.86,"gap_imps":1.39,"ci":0.37,"stakes":3.55,"doubled_share":0.25,"top2":["3S","P"],"q":0.865,"p4":0.413,"tv":1.0,"flip":0.672,"span":false,"trap":true,"damage":false,"interest":100,"p_top_wins":0.629,"p_second_wins":0.236,"winner_by":"EV gap >= 0.5 IMPs","half_stats":[{"gap_imps":0.95,"p_top_wins":0.586,"p_second_wins":0.262},{"gap_imps":1.82,"p_top_wins":0.672,"p_second_wins":0.211}]},"explanations":{"note":"call meanings follow standard 2/1 Game Force","stem":[{"idx":0,"seat":"N","call":"1S","card":{"text":"5+ !S","hcp":[11,20],"minlen":{"C":0,"D":0,"H":0,"S":5}},"text":"1\u2660 (N): 5+\u2660, 11-20"},{"idx":1,"seat":"E","call":"P","card":{"text":"","hcp":[0,14],"minlen":{"C":0,"D":0,"H":0,"S":0}},"text":"Pass (E): 0-14"},{"idx":2,"seat":"S","call":"2S","card":{"text":"calculated bid","hcp":[7,9],"minlen":{"C":0,"D":0,"H":0,"S":3}},"text":"2\u2660 (S): 3+\u2660, 7-9"},{"idx":3,"seat":"W","call":"3D","card":{"text":"bidable suit","hcp":[12,26],"minlen":{"C":0,"D":5,"H":0,"S":0}},"text":"3\u2666 (W): 5+\u2666, 12+"},{"idx":4,"seat":"N","call":"P","card":{"text":"","hcp":[11,16],"minlen":{"C":0,"D":0,"H":0,"S":5}},"text":"Pass (N): 5+\u2660, 11-16"},{"idx":5,"seat":"E","call":"P","card":{"text":"","hcp":[0,11],"minlen":{"C":0,"D":0,"H":0,"S":0}},"text":"Pass (E): 0-11"}],"options":[{"bid":"3S","text":"3\u2660 \u2014 3+\u2660, 7-9. Leads to 3\u2660N 58%, 4\u2666W 21%, 3SXN 7%. Engine: 59%. Best: +1.4 IMPs vs Pass (\u00b10.4), wins 63% of layouts.","card":{"text":"calculated bid","hcp":[7,9],"minlen":{"C":0,"D":0,"H":0,"S":3}}},{"bid":"P","text":"Pass \u2014 7-9. Leads to 3\u2666W 100%. Engine: 59%. -1.4 IMPs vs the top choice (\u00b10.4), wins 24%, pushes 14%.","card":{"text":"","hcp":[7,9],"minlen":{"C":0,"D":0,"H":0,"S":3}}}]},"hero_role":"responder","full_deal":{"N":"AT752.KQJ2.2.Q82","E":"864.54.KQT4.K654","S":"KJ9.T9873.53.AT9","W":"Q3.A6.AJ9876.J73"},"engine_auction_complete":["1S","P","2S","3D","P","P","P"],"policy_trail":[{"idx":0,"seat":"N","chosen":"1S","policy":[["1S",1.2]]},{"idx":1,"seat":"E","chosen":"P","policy":[["P",1.2]]},{"idx":2,"seat":"S","chosen":"2S","policy":[["2S",1.192]]},{"idx":3,"seat":"W","chosen":"3D","policy":[["3D",1.035],["P",0.162]]},{"idx":4,"seat":"N","chosen":"P","policy":[["P",1.029],["3S",0.169]]},{"idx":5,"seat":"E","chosen":"P","policy":[["P",1.129],["5D",0.029]]},{"idx":6,"seat":"S","chosen":"P","policy":[["P",0.592],["3S",0.591]]}],"classification":{"difficulty_score":51.4,"difficulty_level":3,"type":"compete_or_sell","type_reason":"Partner made a competitive raise to 3\u2660 over 3\u2666 is settled at the 2-level/3-level fight; hero with 6-card heart suit but decent trumps must decide whether to compete to 3\u2660 or defend against 3\u2666."}}