{"schema":1,"kind":"bidding","id":"ben1-0007abad","created_at":"2026-07-18T23:31:50+00:00","generator":{"engine":"ben BEN-21GF","seed":502701,"samples":512,"oracle":"none","elapsed_s":11.5},"scoring_form":"IMPs","dealer":"E","vul":"NS","seat":"W","hand":"AK852.AQ3.QJ.Q86","auction":["P","1D","X","P","1H","P","1S","P","2H","P"],"candidates":[{"call":"3H","policy":0.446},{"call":"P","policy":0.291},{"call":"4H","policy":0.272}],"verdict":{"accepted":"P","toss_up":false,"toss_up_set":[],"flags":[],"table":[{"bid":"P","ev_imp_vs_top":2.01,"vs":"3H","ci":0.35,"p_gain":0.66,"p_loss":0.164,"p_push":0.176,"best_share":0.658,"top_contracts":[["2HE",493],["3HE",11],["3DS",5]]},{"bid":"3H","ev_imp_vs_top":-2.01,"vs":"P","ci":0.35,"p_gain":0.164,"p_loss":0.66,"p_push":0.176,"best_share":0.004,"top_contracts":[["4HE",328],["3HE",180],["4HXE",2]]},{"bid":"4H","ev_imp_vs_top":-2.67,"vs":"P","ci":0.39,"p_gain":0.199,"p_loss":0.799,"p_push":0.002,"best_share":0.035,"top_contracts":[["4HE",503],["4HXE",6],["5DXS",3]]}],"dead_options":[{"bid":"3H","best_share":0.0039}]},"difficulty":2.01,"quality":{"n_samples":512,"quality":0.82,"gap_imps":2.01,"ci":0.35,"stakes":4.01,"doubled_share":0.02,"top2":["P","3H"],"q":0.824,"p4":0.756,"tv":0.977,"flip":0.012,"span":true,"trap":true,"damage":false,"interest":100,"p_top_wins":0.66,"p_second_wins":0.164,"winner_by":"EV gap >= 0.5 IMPs","half_stats":[{"gap_imps":2.09,"p_top_wins":0.66,"p_second_wins":0.168},{"gap_imps":1.93,"p_top_wins":0.66,"p_second_wins":0.16}]},"explanations":{"note":"call meanings follow standard 2/1 Game Force","stem":[{"idx":0,"seat":"E","call":"P","card":{"text":"","hcp":[0,11],"minlen":{"C":0,"D":0,"H":0,"S":0}},"text":"Pass (E): 0-11"},{"idx":1,"seat":"S","call":"1D","card":{"text":"3+ !D","hcp":[11,21],"minlen":{"C":0,"D":3,"H":0,"S":0}},"text":"1\u2666 (S): 3+\u2666, 11-21"},{"idx":2,"seat":"W","call":"X","card":{"text":"takeout double","hcp":[12,37],"minlen":{"C":3,"D":0,"H":3,"S":3}},"text":"Dbl (W): takeout double, 12+"},{"idx":3,"seat":"N","call":"P","card":{"text":"","hcp":[0,9],"minlen":{"C":0,"D":0,"H":0,"S":0}},"text":"Pass (N): 0-9"},{"idx":4,"seat":"E","call":"1H","card":{"text":"bidable suit","hcp":[0,9],"minlen":{"C":0,"D":0,"H":4,"S":0}},"text":"1\u2665 (E): 4+\u2665, 0-9"},{"idx":5,"seat":"S","call":"P","card":{"text":"","hcp":[11,19],"minlen":{"C":0,"D":3,"H":0,"S":0}},"text":"Pass (S): 11-19"},{"idx":6,"seat":"W","call":"1S","card":{"text":"bidable suit","hcp":[15,29],"minlen":{"C":3,"D":0,"H":3,"S":4}},"text":"1\u2660 (W): 4+\u2660, 15+"},{"idx":7,"seat":"N","call":"P","card":{"text":"","hcp":[0,9],"minlen":{"C":0,"D":0,"H":0,"S":0}},"text":"Pass (N): 0-9"},{"idx":8,"seat":"E","call":"2H","card":{"text":"bidable suit","hcp":[3,7],"minlen":{"C":0,"D":0,"H":5,"S":0}},"text":"2\u2665 (E): 5+\u2665, 3-7"},{"idx":9,"seat":"S","call":"P","card":{"text":"","hcp":[11,19],"minlen":{"C":0,"D":3,"H":0,"S":0}},"text":"Pass (S): 11-19"}],"options":[{"bid":"P","text":"Pass \u2014 4+\u2660, 15-18. Leads to 2\u2665E 96%, 3\u2665E 2%, 3\u2666S 1%. Engine: 29%. Best: +2.0 IMPs vs 3\u2665 (\u00b10.3), wins 66% of layouts.","card":{"text":"","hcp":[15,18],"minlen":{"C":3,"D":0,"H":3,"S":4}}},{"bid":"3H","text":"3\u2665 \u2014 4+\u2660, 3+\u2665, 18-20. Leads to 4\u2665E 64%, 3\u2665E 35%, 4HXE 0%. Engine: 45%. -2.0 IMPs vs the top choice (\u00b10.3), wins 16%, pushes 18%. Never the winner on any simulated layout.","card":{"text":"calculated bid","hcp":[18,20],"minlen":{"C":3,"D":0,"H":3,"S":4}}},{"bid":"4H","text":"4\u2665 \u2014 4+\u2660, 3+\u2665, 18+. Leads to 4\u2665E 98%, 4HXE 1%, 5DXS 1%. Engine: 27%. -2.7 IMPs vs the top choice (\u00b10.4), wins 20%, pushes 0%.","card":{"text":"calculated bid","hcp":[18,29],"minlen":{"C":3,"D":0,"H":3,"S":4}}}]},"hero_role":"overcaller","full_deal":{"N":"9643.875.952.KJ5","E":"J7.KJT94.743.T74","S":"QT.62.AKT86.A932","W":"AK852.AQ3.QJ.Q86"},"engine_auction_complete":["P","1D","X","P","1H","P","1S","P","2H","P","3H","P","P","P"],"policy_trail":[{"idx":0,"seat":"E","chosen":"P","policy":[["P",1.2]]},{"idx":1,"seat":"S","chosen":"1D","policy":[["1D",1.2]]},{"idx":2,"seat":"W","chosen":"X","policy":[["X",1.19]]},{"idx":3,"seat":"N","chosen":"P","policy":[["P",1.188]]},{"idx":4,"seat":"E","chosen":"1H","policy":[["1H",1.179],["2H",0.018]]},{"idx":5,"seat":"S","chosen":"P","policy":[["P",0.809],["2C",0.291]]},{"idx":6,"seat":"W","chosen":"1S","policy":[["1S",1.176],["2S",0.023]]},{"idx":7,"seat":"N","chosen":"P","policy":[["P",1.2]]},{"idx":8,"seat":"E","chosen":"2H","policy":[["2H",0.921],["3H",0.2],["P",0.025]]},{"idx":9,"seat":"S","chosen":"P","policy":[["P",1.193]]},{"idx":10,"seat":"W","chosen":"3H","policy":[["3H",0.446],["P",0.291],["4H",0.272]]},{"idx":11,"seat":"N","chosen":"P","policy":[["P",1.2]]},{"idx":12,"seat":"E","chosen":"P","policy":[["P",0.726],["4H",0.473]]},{"idx":13,"seat":"S","chosen":"P","policy":[["P",1.2]]}],"classification":{"difficulty_score":54.8,"difficulty_level":3}}