{"schema":1,"id":"ben1-00000c8f","created_at":"2026-07-17T06:48:22+00:00","generator":{"engine":"ben BEN-21GF","seed":3215,"samples":128,"oracle":"none","elapsed_s":14.7},"scoring_form":"IMPs","dealer":"W","vul":"None","seat":"N","hand":"J98654.T.K762.J6","auction":["1C"],"candidates":[{"call":"P","policy":0.513},{"call":"2S","policy":0.486}],"verdict":{"accepted":"","toss_up":true,"toss_up_set":["P","2S"],"flags":[],"table":[{"bid":"P","ev_imp_vs_top":0.0,"ci":0.95,"p_gain":0.438,"p_push":0.164,"best_share":0.445,"top_contracts":[["3NE",21],["2NE",18],["2CW",15]]},{"bid":"2S","ev_imp_vs_top":-0.35,"ci":0.95,"p_gain":0.398,"p_push":0.164,"best_share":0.422,"top_contracts":[["2SXN",15],["3HE",14],["3CS",14]]}],"dead_options":[]},"difficulty":0.35,"quality":{"n_samples":128,"quality":0.98,"gap_imps":0.35,"ci":0.95,"stakes":4.49,"doubled_share":0.34,"top2":["P","2S"],"q":0.836,"p4":0.5,"tv":0.812,"flip":0.555,"span":true,"trap":false,"damage":true,"interest":102},"explanations":{"note":"meanings are empirical \u2014 measured over layouts consistent with the auction under the engine's 2/1 style, not quoted from a rulebook","stem":[{"idx":0,"seat":"W","call":"1C","category":"opening","convention":null,"artificial":false,"double_type":null,"band":{"n":128,"hcp_p10":11.0,"hcp_p90":17.0,"hcp_avg":13.3515625,"len_avg":{"S":2.109375,"H":3.21875,"D":2.3203125,"C":5.3515625},"len4plus":{"S":0.09375,"H":0.453125,"D":0.0859375,"C":0.9453125},"len5plus":{"S":0.0,"H":0.015625,"D":0.0,"C":0.7890625},"balanced_share":0.3125},"n":128,"text":"1\u2663 (W): opening \u2014 11-17 HCP, 5.4 \u2663 on average (n=128, measured)"}],"options":[{"bid":"P","text":"Pass \u2014 pass: shows 4-11 HCP, balanced 66% of the time (n=128, measured). Next call is usually 1\u2665 (71%); 1\u2666 (13%); 1\u2660 (7%). A strong engine chooses this 51% of the time here. Where it leads: 3NE (16%), 2NE (14%), 2CW (12%). The panel would split: Pass, 2\u2660 scored within the noise (gap +0.3 IMPs, \u00b10.9).","category":"pass","convention":null,"double_type":null},{"bid":"2S","text":"2\u2660 \u2014 jump overcall: shows 5-9 HCP, 6.1 \u2660 on average (n=128, measured). Next call is usually Double (41%); Pass (25%); 3\u2665 (20%). A strong engine chooses this 49% of the time here. Where it leads: 2SXN (12%), 3HE (11%), 3CS (11%). Scored -0.3 IMPs vs the top choice (\u00b10.9); wins on 40% of layouts, pushes on 16%.","category":"jump overcall","convention":null,"double_type":null}]},"hero_role":"other","full_deal":{"N":"J98654.T.K762.J6","E":"K73.J732.Q85.K87","S":"QT.AKQ954.T9.942","W":"A2.86.AJ43.AQT53"},"engine_auction_complete":["1C","P","1H","P","1NT","P","P","P"],"policy_trail":[{"idx":0,"seat":"W","chosen":"1C","policy":[["1C",0.999]]},{"idx":1,"seat":"N","chosen":"P","policy":[["P",0.513],["2S",0.486]]},{"idx":2,"seat":"E","chosen":"1H","policy":[["1H",1.0]]},{"idx":3,"seat":"S","chosen":"P","policy":[["P",0.614],["2H",0.382]]},{"idx":4,"seat":"W","chosen":"1NT","policy":[["1NT",0.908],["2D",0.092]]},{"idx":5,"seat":"N","chosen":"P","policy":[["P",0.996]]},{"idx":6,"seat":"E","chosen":"P","policy":[["P",0.993]]},{"idx":7,"seat":"S","chosen":"P","policy":[["P",0.999]]}]}