{"schema":1,"kind":"bidding","id":"ben1-000114e5","created_at":"2026-07-18T07:28:09+00:00","generator":{"engine":"ben BEN-21GF","seed":70885,"samples":512,"oracle":"none","elapsed_s":8.1},"scoring_form":"IMPs","dealer":"S","vul":"Both","seat":"N","hand":"K63.3.A98743.KQ9","auction":["3C","P"],"candidates":[{"call":"P","policy":0.48},{"call":"5C","policy":0.411},{"call":"4C","policy":0.227}],"verdict":{"accepted":"5C","toss_up":false,"toss_up_set":[],"flags":[],"table":[{"bid":"5C","ev_imp_vs_top":0.99,"vs":"4C","ci":0.66,"p_gain":0.41,"p_loss":0.48,"p_push":0.109,"best_share":0.26,"top_contracts":[["5CS",392],["5CXS",115],["5HXE",3]]},{"bid":"4C","ev_imp_vs_top":-0.99,"vs":"5C","ci":0.66,"p_gain":0.48,"p_loss":0.41,"p_push":0.109,"best_share":0.254,"top_contracts":[["4CS",339],["5CXS",71],["5CS",37]]},{"bid":"P","ev_imp_vs_top":-1.39,"vs":"5C","ci":0.65,"p_gain":0.369,"p_loss":0.424,"p_push":0.207,"best_share":0.186,"top_contracts":[["3CS",129],["5CS",96],["5CXS",86]]}],"dead_options":[]},"difficulty":0.99,"quality":{"n_samples":512,"quality":0.88,"gap_imps":0.99,"ci":0.66,"stakes":6.71,"doubled_share":0.3,"top2":["5C","4C"],"q":0.891,"p4":0.641,"tv":0.781,"flip":0.104,"span":true,"trap":true,"damage":false,"interest":100,"p_top_wins":0.41,"p_second_wins":0.48,"winner_by":"EV gap >= 0.5 IMPs","half_stats":[{"gap_imps":1.42,"p_top_wins":0.43,"p_second_wins":0.453},{"gap_imps":0.56,"p_top_wins":0.391,"p_second_wins":0.508}]},"explanations":{"note":"call meanings follow standard 2/1 Game Force","stem":[{"idx":0,"seat":"S","call":"3C","card":{"text":"preemptive","hcp":[5,10],"minlen":{"C":7,"D":0,"H":0,"S":0}},"text":"3\u2663 (S): preemptive, 7+\u2663, 5-10"},{"idx":1,"seat":"W","call":"P","card":{"text":"","hcp":[0,18],"minlen":{"C":0,"D":0,"H":0,"S":0}},"text":"Pass (W): 0-18"}],"options":[{"bid":"5C","text":"5\u2663 \u2014 3+\u2663, 4+. Leads to 5\u2663S 77%, 5CXS 22%, 5HXE 1%. Engine: 41%. Best: +1.0 IMPs vs 4\u2663 (\u00b10.7), wins 41% of layouts.","card":{"text":"calculated bid","hcp":[4,26],"minlen":{"C":3,"D":0,"H":0,"S":0}}},{"bid":"4C","text":"4\u2663 \u2014 preemptive, 4-9. Leads to 4\u2663S 66%, 5CXS 14%, 5\u2663S 7%. Engine: 23%. -1.0 IMPs vs the top choice (\u00b10.7), wins 48%, pushes 11%.","card":{"text":"preemptive","hcp":[4,9],"minlen":{"C":2,"D":0,"H":0,"S":0}}},{"bid":"P","text":"Pass \u2014 0-17. Leads to 3\u2663S 25%, 5\u2663S 19%, 5CXS 17%. Engine: 48%. -1.4 IMPs vs the top choice (\u00b10.7), wins 37%, pushes 21%.","card":{"text":"","hcp":[0,17],"minlen":{"C":0,"D":0,"H":0,"S":0}}}]},"hero_role":"responder","full_deal":{"N":"K63.3.A98743.KQ9","E":"AT987.AJT5.J6.A6","S":"J.Q974.K.JT75432","W":"Q542.K862.QT52.8"},"engine_auction_complete":["3C","P","P","3S","P","P","4C","P","P","P"],"policy_trail":[{"idx":0,"seat":"S","chosen":"3C","policy":[["3C",0.647],["P",0.553]]},{"idx":1,"seat":"W","chosen":"P","policy":[["P",1.2]]},{"idx":2,"seat":"N","chosen":"P","policy":[["P",0.48],["5C",0.411],["4C",0.227]]},{"idx":3,"seat":"E","chosen":"3S","policy":[["3S",1.162],["P",0.02]]},{"idx":4,"seat":"S","chosen":"P","policy":[["P",1.2]]},{"idx":5,"seat":"W","chosen":"P","policy":[["P",1.032],["4S",0.136]]},{"idx":6,"seat":"N","chosen":"4C","policy":[["4C",0.954],["P",0.204]]},{"idx":7,"seat":"E","chosen":"P","policy":[["P",1.198]]},{"idx":8,"seat":"S","chosen":"P","policy":[["P",1.199]]},{"idx":9,"seat":"W","chosen":"P","policy":[["P",0.718],["4S",0.475]]}],"classification":{"difficulty_score":62.6,"difficulty_level":4,"type":"invite_or_game","type_reason":"With a fit for partner's preempted clubs plus outside values (A\u2666, KQ\u2663, singleton \u2665), hero must decide whether to bid game (5\u2663) or hold back, a constructive raise-level decision."}}