{"schema":1,"kind":"bidding","id":"ben1-01c9f14b","created_at":"2026-07-19T00:17:33+00:00","generator":{"engine":"ben BEN-21GF","seed":30011723,"samples":512,"oracle":"none","elapsed_s":31.3},"scoring_form":"IMPs","dealer":"W","vul":"None","seat":"N","hand":"743.73.Q8543.K92","auction":["P","P","1H","1NT","P","P","2H","P","P"],"candidates":[{"call":"P","policy":0.595},{"call":"3D","policy":0.537}],"verdict":{"accepted":"3D","toss_up":false,"toss_up_set":[],"flags":[],"table":[{"bid":"3D","ev_imp_vs_top":1.09,"vs":"P","ci":0.36,"p_gain":0.572,"p_loss":0.264,"p_push":0.164,"best_share":0.648,"top_contracts":[["3DN",207],["3HE",102],["4DN",86]]},{"bid":"P","ev_imp_vs_top":-1.09,"vs":"3D","ci":0.36,"p_gain":0.264,"p_loss":0.572,"p_push":0.164,"best_share":0.283,"top_contracts":[["2HE",512]]}],"dead_options":[]},"difficulty":1.09,"quality":{"n_samples":512,"quality":0.86,"gap_imps":1.09,"ci":0.36,"stakes":3.46,"doubled_share":0.37,"top2":["3D","P"],"q":0.836,"p4":0.407,"tv":1.0,"flip":0.596,"span":false,"trap":true,"damage":true,"interest":112,"p_top_wins":0.572,"p_second_wins":0.264,"winner_by":"EV gap >= 0.5 IMPs","half_stats":[{"gap_imps":0.91,"p_top_wins":0.57,"p_second_wins":0.309},{"gap_imps":1.27,"p_top_wins":0.574,"p_second_wins":0.219}]},"explanations":{"note":"call meanings follow standard 2/1 Game Force","stem":[{"idx":0,"seat":"W","call":"P","card":{"text":"","hcp":[0,11],"minlen":{"C":0,"D":0,"H":0,"S":0}},"text":"Pass (W): 0-11"},{"idx":1,"seat":"N","call":"P","card":{"text":"","hcp":[0,11],"minlen":{"C":0,"D":0,"H":0,"S":0}},"text":"Pass (N): 0-11"},{"idx":2,"seat":"E","call":"1H","card":{"text":"5+ !H","hcp":[11,20],"minlen":{"C":0,"D":0,"H":5,"S":0}},"text":"1\u2665 (E): 5+\u2665, 11-20"},{"idx":3,"seat":"S","call":"1NT","card":{"text":"NT style","hcp":[15,17],"minlen":{"C":2,"D":2,"H":2,"S":2}},"text":"1NT (S): NT style, 15-17"},{"idx":4,"seat":"W","call":"P","card":{"text":"","hcp":[0,10],"minlen":{"C":0,"D":0,"H":0,"S":0}},"text":"Pass (W): 0-10"},{"idx":5,"seat":"N","call":"P","card":{"text":"","hcp":[0,9],"minlen":{"C":0,"D":0,"H":0,"S":0}},"text":"Pass (N): 0-9"},{"idx":6,"seat":"E","call":"2H","card":{"text":"bidable suit","hcp":[13,17],"minlen":{"C":0,"D":0,"H":6,"S":0}},"text":"2\u2665 (E): 6+\u2665, 13-17"},{"idx":7,"seat":"S","call":"P","card":{"text":"","hcp":[15,17],"minlen":{"C":2,"D":2,"H":2,"S":2}},"text":"Pass (S): 15-17"},{"idx":8,"seat":"W","call":"P","card":{"text":"","hcp":[0,10],"minlen":{"C":0,"D":0,"H":0,"S":0}},"text":"Pass (W): 0-10"}],"options":[{"bid":"3D","text":"3\u2666 \u2014 5+\u2666, 5-9. Leads to 3\u2666N 40%, 3\u2665E 20%, 4\u2666N 17%. Engine: 54%. Best: +1.1 IMPs vs Pass (\u00b10.4), wins 57% of layouts.","card":{"text":"bidable suit","hcp":[5,9],"minlen":{"C":0,"D":5,"H":0,"S":0}}},{"bid":"P","text":"Pass \u2014 0-9. Leads to 2\u2665E 100%. Engine: 60%. -1.1 IMPs vs the top choice (\u00b10.4), wins 26%, pushes 16%.","card":{"text":"","hcp":[0,9],"minlen":{"C":0,"D":0,"H":0,"S":0}}}]},"hero_role":"advancer","full_deal":{"N":"743.73.Q8543.K92","E":"KJ.QJ8652.A6.T65","S":"T952.AK4.KJ9.AQ7","W":"AQ86.T9.T72.J843"},"engine_auction_complete":["P","P","1H","1NT","P","P","2H","P","P","P"],"policy_trail":[{"idx":0,"seat":"W","chosen":"P","policy":[["P",1.2]]},{"idx":1,"seat":"N","chosen":"P","policy":[["P",1.2]]},{"idx":2,"seat":"E","chosen":"1H","policy":[["1H",1.124]]},{"idx":3,"seat":"S","chosen":"1NT","policy":[["1NT",0.867],["X",0.317]]},{"idx":4,"seat":"W","chosen":"P","policy":[["P",1.197]]},{"idx":5,"seat":"N","chosen":"P","policy":[["P",1.198]]},{"idx":6,"seat":"E","chosen":"2H","policy":[["2H",0.787],["P",0.412]]},{"idx":7,"seat":"S","chosen":"P","policy":[["P",1.196]]},{"idx":8,"seat":"W","chosen":"P","policy":[["P",0.706],["3H",0.466]]},{"idx":9,"seat":"N","chosen":"P","policy":[["P",0.595],["3D",0.537]]}],"classification":{"difficulty_score":57.3,"difficulty_level":4}}