{"schema":1,"kind":"bidding","id":"ben1-00011b2c","created_at":"2026-07-18T07:53:38+00:00","generator":{"engine":"ben BEN-21GF","seed":72492,"samples":512,"oracle":"none","elapsed_s":10.0},"scoring_form":"IMPs","dealer":"S","vul":"EW","seat":"N","hand":"AJT95.Q.A42.T953","auction":["2D","2H"],"candidates":[{"call":"3D","policy":0.69},{"call":"4D","policy":0.424}],"verdict":{"accepted":"4D","toss_up":false,"toss_up_set":[],"flags":[],"table":[{"bid":"4D","ev_imp_vs_top":0.92,"vs":"3D","ci":0.5,"p_gain":0.426,"p_loss":0.197,"p_push":0.377,"best_share":0.426,"top_contracts":[["4HW",355],["4DS",95],["4DXS",58]]},{"bid":"3D","ev_imp_vs_top":-0.92,"vs":"4D","ci":0.5,"p_gain":0.197,"p_loss":0.426,"p_push":0.377,"best_share":0.199,"top_contracts":[["3HW",247],["4HW",238],["3DS",13]]}],"dead_options":[]},"difficulty":0.92,"quality":{"n_samples":512,"quality":0.87,"gap_imps":0.92,"ci":0.5,"stakes":4.09,"doubled_share":0.26,"top2":["4D","3D"],"q":0.623,"p4":0.395,"tv":0.525,"flip":0.273,"span":true,"trap":true,"damage":true,"interest":113.5,"p_top_wins":0.426,"p_second_wins":0.197,"winner_by":"EV gap >= 0.5 IMPs","half_stats":[{"gap_imps":1.0,"p_top_wins":0.473,"p_second_wins":0.207},{"gap_imps":0.83,"p_top_wins":0.379,"p_second_wins":0.188}]},"explanations":{"note":"call meanings follow standard 2/1 Game Force","stem":[{"idx":0,"seat":"S","call":"2D","card":{"text":"Weak natural 2D","hcp":[3,10],"minlen":{"C":0,"D":6,"H":0,"S":0}},"text":"2\u2666 (S): Weak natural 2D, 6+\u2666, 3-10"},{"idx":1,"seat":"W","call":"2H","card":{"text":"bidable suit","hcp":[12,17],"minlen":{"C":0,"D":0,"H":5,"S":0}},"text":"2\u2665 (W): 5+\u2665, 12-17"}],"options":[{"bid":"4D","text":"4\u2666 \u2014 preemptive, 3+\u2666, 4-11. Leads to 4\u2665W 69%, 4\u2666S 19%, 4DXS 11%. Engine: 42%. Best: +0.9 IMPs vs 3\u2666 (\u00b10.5), wins 43% of layouts.","card":{"text":"preemptive","hcp":[4,11],"minlen":{"C":0,"D":3,"H":0,"S":0}}},{"bid":"3D","text":"3\u2666 \u2014 12-18. Leads to 3\u2665W 48%, 4\u2665W 46%, 3\u2666S 3%. Engine: 69%. -0.9 IMPs vs the top choice (\u00b10.5), wins 20%, pushes 38%.","card":{"text":"calculated bid","hcp":[12,18],"minlen":{"C":0,"D":2,"H":0,"S":0}}}]},"hero_role":"responder","full_deal":{"N":"AJT95.Q.A42.T953","E":"K76.T9532.Q3.J64","S":"432.86.KJT986.Q2","W":"Q8.AKJ74.75.AK87"},"engine_auction_complete":["2D","2H","3D","3H","P","4H","P","P","P"],"policy_trail":[{"idx":0,"seat":"S","chosen":"2D","policy":[["2D",1.151]]},{"idx":1,"seat":"W","chosen":"2H","policy":[["2H",1.086],["X",0.083]]},{"idx":2,"seat":"N","chosen":"3D","policy":[["3D",0.69],["4D",0.424]]},{"idx":3,"seat":"E","chosen":"3H","policy":[["3H",0.8],["4H",0.367]]},{"idx":4,"seat":"S","chosen":"P","policy":[["P",1.197]]},{"idx":5,"seat":"W","chosen":"4H","policy":[["4H",0.818],["P",0.301]]},{"idx":6,"seat":"N","chosen":"P","policy":[["P",1.15]]},{"idx":7,"seat":"E","chosen":"P","policy":[["P",1.2]]},{"idx":8,"seat":"S","chosen":"P","policy":[["P",1.197]]}],"classification":{"difficulty_score":64.6,"difficulty_level":4,"type":"preempt_decision","type_reason":"Raising partner's weak 2D with support and a good hand shape; the 3D vs 4D choice is purely about how far to preempt/obstruct the opponents' heart auction."}}