{"schema":1,"kind":"bidding","id":"ben1-00049861","created_at":"2026-07-18T20:53:13+00:00","generator":{"engine":"ben BEN-21GF","seed":301153,"samples":512,"oracle":"none","elapsed_s":26.3},"scoring_form":"IMPs","dealer":"S","vul":"NS","seat":"E","hand":"KQJ976.T943.A.K3","auction":["P","P","P","1S","P","1NT","P","2H","P","3H","P"],"candidates":[{"call":"P","policy":0.666},{"call":"4H","policy":0.507}],"verdict":{"accepted":"4H","toss_up":false,"toss_up_set":[],"flags":[],"table":[{"bid":"4H","ev_imp_vs_top":0.95,"vs":"P","ci":0.45,"p_gain":0.504,"p_loss":0.496,"p_push":0.0,"best_share":0.504,"top_contracts":[["4HE",512]]},{"bid":"P","ev_imp_vs_top":-0.95,"vs":"4H","ci":0.45,"p_gain":0.496,"p_loss":0.504,"p_push":0.0,"best_share":0.496,"top_contracts":[["3HE",512]]}],"dead_options":[]},"difficulty":0.95,"quality":{"n_samples":512,"quality":0.85,"gap_imps":0.95,"ci":0.45,"stakes":5.09,"doubled_share":0.0,"top2":["4H","P"],"q":1.0,"p4":0.863,"tv":1.0,"flip":0.0,"span":true,"trap":true,"damage":false,"interest":100,"p_top_wins":0.504,"p_second_wins":0.496,"winner_by":"EV gap >= 0.5 IMPs","half_stats":[{"gap_imps":0.85,"p_top_wins":0.5,"p_second_wins":0.5},{"gap_imps":1.05,"p_top_wins":0.508,"p_second_wins":0.492}]},"explanations":{"note":"call meanings follow standard 2/1 Game Force","stem":[{"idx":0,"seat":"S","call":"P","card":{"text":"","hcp":[0,11],"minlen":{"C":0,"D":0,"H":0,"S":0}},"text":"Pass (S): 0-11"},{"idx":1,"seat":"W","call":"P","card":{"text":"","hcp":[0,11],"minlen":{"C":0,"D":0,"H":0,"S":0}},"text":"Pass (W): 0-11"},{"idx":2,"seat":"N","call":"P","card":{"text":"","hcp":[0,11],"minlen":{"C":0,"D":0,"H":0,"S":0}},"text":"Pass (N): 0-11"},{"idx":3,"seat":"E","call":"1S","card":{"text":"5+ !S","hcp":[11,20],"minlen":{"C":0,"D":0,"H":0,"S":5}},"text":"1\u2660 (E): 5+\u2660, 11-20"},{"idx":4,"seat":"S","call":"P","card":{"text":"","hcp":[0,11],"minlen":{"C":0,"D":0,"H":0,"S":0}},"text":"Pass (S): 0-11"},{"idx":5,"seat":"W","call":"1NT","card":{"text":"balanced","hcp":[6,11],"minlen":{"C":0,"D":0,"H":0,"S":0}},"text":"1NT (W): 6-11"},{"idx":6,"seat":"N","call":"P","card":{"text":"","hcp":[0,11],"minlen":{"C":0,"D":0,"H":0,"S":0}},"text":"Pass (N): 0-11"},{"idx":7,"seat":"E","call":"2H","card":{"text":"bidable suit","hcp":[11,14],"minlen":{"C":0,"D":0,"H":4,"S":5}},"text":"2\u2665 (E): 5+\u2660, 4+\u2665, 11-14"},{"idx":8,"seat":"S","call":"P","card":{"text":"","hcp":[0,11],"minlen":{"C":0,"D":0,"H":0,"S":0}},"text":"Pass (S): 0-11"},{"idx":9,"seat":"W","call":"3H","card":{"text":"calculated bid","hcp":[9,11],"minlen":{"C":0,"D":0,"H":4,"S":0}},"text":"3\u2665 (W): 4+\u2665, 9-11"},{"idx":10,"seat":"N","call":"P","card":{"text":"","hcp":[0,11],"minlen":{"C":0,"D":0,"H":0,"S":0}},"text":"Pass (N): 0-11"}],"options":[{"bid":"4H","text":"4\u2665 \u2014 5+\u2660, 4+\u2665, 11-14. Leads to 4\u2665E 100%. Engine: 51%. Best: +0.9 IMPs vs Pass (\u00b10.5), wins 50% of layouts.","card":{"text":"calculated bid","hcp":[11,14],"minlen":{"C":0,"D":0,"H":4,"S":5}}},{"bid":"P","text":"Pass \u2014 5+\u2660, 4+\u2665, 11-14. Leads to 3\u2665E 100%. Engine: 67%. -0.9 IMPs vs the top choice (\u00b10.5), wins 50%, pushes 0%.","card":{"text":"","hcp":[11,14],"minlen":{"C":0,"D":0,"H":4,"S":5}}}]},"hero_role":"opener","full_deal":{"N":"A3.A7.T8762.J965","E":"KQJ976.T943.A.K3","S":"542.Q65.J94.AQT8","W":"T8.KJ82.KQ53.742"},"engine_auction_complete":["P","P","P","1S","P","1NT","P","2H","P","3H","P","P","P"],"policy_trail":[{"idx":0,"seat":"S","chosen":"P","policy":[["P",1.2]]},{"idx":1,"seat":"W","chosen":"P","policy":[["P",1.2]]},{"idx":2,"seat":"N","chosen":"P","policy":[["P",1.198]]},{"idx":3,"seat":"E","chosen":"1S","policy":[["1S",1.2]]},{"idx":4,"seat":"S","chosen":"P","policy":[["P",1.2]]},{"idx":5,"seat":"W","chosen":"1NT","policy":[["1NT",1.2]]},{"idx":6,"seat":"N","chosen":"P","policy":[["P",1.2]]},{"idx":7,"seat":"E","chosen":"2H","policy":[["2H",1.191]]},{"idx":8,"seat":"S","chosen":"P","policy":[["P",1.2]]},{"idx":9,"seat":"W","chosen":"3H","policy":[["3H",0.824],["P",0.371]]},{"idx":10,"seat":"N","chosen":"P","policy":[["P",1.2]]},{"idx":11,"seat":"E","chosen":"P","policy":[["P",0.666],["4H",0.507]]},{"idx":12,"seat":"S","chosen":"P","policy":[["P",1.2]]}],"classification":{"difficulty_score":62.9,"difficulty_level":4}}