{"schema":1,"id":"ben1-00001402","created_at":"2026-07-17T10:14:17+00:00","generator":{"engine":"ben BEN-21GF","seed":5122,"samples":128,"oracle":"none","elapsed_s":2.2},"scoring_form":"IMPs","dealer":"W","vul":"None","seat":"N","hand":"42.964.J852.AJ42","auction":["P","P","P","1S","P","1NT","P","3C","P"],"candidates":[{"call":"4C","policy":0.555},{"call":"3S","policy":0.29},{"call":"3NT","policy":0.228}],"verdict":{"accepted":"4C","toss_up":false,"toss_up_set":[],"flags":[],"table":[{"bid":"4C","ev_imp_vs_top":1.72,"vs":"3S","ci":0.93,"p_gain":0.5,"p_loss":0.312,"p_push":0.188,"best_share":0.523,"top_contracts":[["4CS",70],["5CS",52],["6CS",5]]},{"bid":"3S","ev_imp_vs_top":-1.72,"vs":"4C","ci":0.93,"p_gain":0.312,"p_loss":0.5,"p_push":0.188,"best_share":0.156,"top_contracts":[["3NN",66],["3SS",40],["4SS",21]]},{"bid":"3NT","ev_imp_vs_top":-3.19,"vs":"4C","ci":0.95,"p_gain":0.195,"p_loss":0.703,"p_push":0.102,"best_share":0.016,"top_contracts":[["3NN",117],["4SS",11]]}],"dead_options":[]},"difficulty":1.72,"quality":{"n_samples":128,"quality":0.86,"gap_imps":1.72,"ci":0.93,"stakes":4.3,"doubled_share":0.0,"top2":["4C","3S"],"q":0.812,"p4":0.531,"tv":1.0,"flip":0.0,"span":true,"trap":false,"damage":false,"interest":80,"p_top_wins":0.5,"p_second_wins":0.312,"winner_by":"EV gap >= 0.5 IMPs"},"explanations":{"note":"call meanings follow standard 2/1 Game Force","stem":[{"idx":0,"seat":"W","call":"P","category":"pass","convention":null,"artificial":false,"double_type":null,"card":{"text":"","hcp":[0,11],"minlen":{"C":0,"D":0,"H":0,"S":0}},"text":"Pass (W): limited \u2014 at most 11 HCP"},{"idx":1,"seat":"N","call":"P","category":"pass","convention":null,"artificial":false,"double_type":null,"card":{"text":"","hcp":[0,11],"minlen":{"C":0,"D":0,"H":0,"S":0}},"text":"Pass (N): limited \u2014 at most 11 HCP"},{"idx":2,"seat":"E","call":"P","category":"pass","convention":null,"artificial":false,"double_type":null,"card":{"text":"","hcp":[0,11],"minlen":{"C":0,"D":0,"H":0,"S":0}},"text":"Pass (E): limited \u2014 at most 11 HCP"},{"idx":3,"seat":"S","call":"1S","category":"opening","convention":null,"artificial":false,"double_type":null,"card":{"text":"5+ !S","hcp":[11,20],"minlen":{"C":0,"D":0,"H":0,"S":5}},"text":"1\u2660 (S): 5+ \u2660"},{"idx":4,"seat":"W","call":"P","category":"pass","convention":null,"artificial":false,"double_type":null,"card":{"text":"","hcp":[0,11],"minlen":{"C":0,"D":0,"H":0,"S":0}},"text":"Pass (W): limited \u2014 at most 11 HCP"},{"idx":5,"seat":"N","call":"1NT","category":"notrump","convention":null,"artificial":false,"double_type":null,"card":{"text":"balanced","hcp":[6,11],"minlen":{"C":0,"D":0,"H":0,"S":0}},"text":"1NT (N): balanced \u2014 6-11 HCP"},{"idx":6,"seat":"E","call":"P","category":"pass","convention":null,"artificial":false,"double_type":null,"card":{"text":"","hcp":[0,11],"minlen":{"C":0,"D":0,"H":0,"S":0}},"text":"Pass (E): limited \u2014 at most 11 HCP"},{"idx":7,"seat":"S","call":"3C","category":"jump new-suit","convention":null,"artificial":false,"double_type":null,"card":{"text":"bidable suit","hcp":[17,20],"minlen":{"C":4,"D":0,"H":0,"S":5}},"text":"3\u2663 (S): 17-20 HCP, 5+ \u2660, 4+ \u2663"},{"idx":8,"seat":"W","call":"P","category":"pass","convention":null,"artificial":false,"double_type":null,"card":{"text":"","hcp":[0,11],"minlen":{"C":0,"D":0,"H":0,"S":0}},"text":"Pass (W): limited \u2014 at most 11 HCP"}],"options":[{"bid":"4C","text":"4\u2663 \u2014 6-11 HCP, 4+ \u2663. Next call is usually Pass (100%); most common continuation: Pass Pass Pass (55%). A strong engine chooses this 56% of the time here. Where it leads: 4CS (55%), 5CS (41%), 6CS (4%). The winner (EV gap >= 0.5 IMPs): +1.7 IMPs vs 3\u2660 (\u00b10.9); wins on 50% of layouts against 31%.","category":"raise","convention":null,"double_type":null},{"bid":"3S","text":"3\u2660 \u2014 6-11 HCP. Next call is usually Pass (100%); most common continuation: Pass 3NT Pass (52%). A strong engine chooses this 29% of the time here. Where it leads: 3NN (52%), 3SS (31%), 4SS (16%). Scored -1.7 IMPs vs the top choice (\u00b10.9); wins on 31% of layouts, pushes on 19%.","category":"raise","convention":null,"double_type":null},{"bid":"3NT","text":"3NT \u2014 6-11 HCP. Next call is usually Pass (100%); most common continuation: Pass Pass Pass (91%). A strong engine chooses this 23% of the time here. Where it leads: 3NN (91%), 4SS (9%). Scored -3.2 IMPs vs the top choice (\u00b10.9); wins on 20% of layouts, pushes on 10%.","category":"notrump","convention":null,"double_type":null}]},"hero_role":"responder","full_deal":{"N":"42.964.J852.AJ42","E":"J7.AT87.K93.9853","S":"AQ986.K.AT4.KQ76","W":"KT53.QJ532.Q76.T"},"engine_auction_complete":["P","P","P","1S","P","1NT","P","3C","P","4C","P","P","P"],"policy_trail":[{"idx":0,"seat":"W","chosen":"P","policy":[["P",1.2]]},{"idx":1,"seat":"N","chosen":"P","policy":[["P",1.2]]},{"idx":2,"seat":"E","chosen":"P","policy":[["P",1.2]]},{"idx":3,"seat":"S","chosen":"1S","policy":[["1S",1.199]]},{"idx":4,"seat":"W","chosen":"P","policy":[["P",1.2]]},{"idx":5,"seat":"N","chosen":"1NT","policy":[["1NT",1.195]]},{"idx":6,"seat":"E","chosen":"P","policy":[["P",1.2]]},{"idx":7,"seat":"S","chosen":"3C","policy":[["3C",1.194]]},{"idx":8,"seat":"W","chosen":"P","policy":[["P",1.2]]},{"idx":9,"seat":"N","chosen":"4C","policy":[["4C",0.555],["3S",0.29],["3NT",0.228]]},{"idx":10,"seat":"E","chosen":"P","policy":[["P",1.2]]},{"idx":11,"seat":"S","chosen":"P","policy":[["P",0.577],["5C",0.526]]},{"idx":12,"seat":"W","chosen":"P","policy":[["P",1.2]]}]}