{"schema":1,"kind":"bidding","id":"ben1-01c9ee86","created_at":"2026-07-18T23:59:25+00:00","generator":{"engine":"ben BEN-21GF","seed":30011014,"samples":512,"oracle":"none","elapsed_s":21.4},"scoring_form":"IMPs","dealer":"N","vul":"EW","seat":"N","hand":"K.854.962.AKJ952","auction":["1C","2S","P","P"],"candidates":[{"call":"P","policy":0.647},{"call":"3C","policy":0.436},{"call":"X","policy":0.117}],"verdict":{"accepted":"P","toss_up":false,"toss_up_set":[],"flags":[],"table":[{"bid":"P","ev_imp_vs_top":1.22,"vs":"3C","ci":0.52,"p_gain":0.402,"p_loss":0.424,"p_push":0.174,"best_share":0.221,"top_contracts":[["2SE",512]]},{"bid":"3C","ev_imp_vs_top":-1.22,"vs":"P","ci":0.52,"p_gain":0.424,"p_loss":0.402,"p_push":0.174,"best_share":0.355,"top_contracts":[["3CN",110],["4CN",101],["4SE",74]]},{"bid":"X","ev_imp_vs_top":-3.1,"vs":"P","ci":0.61,"p_gain":0.309,"p_loss":0.457,"p_push":0.234,"best_share":0.201,"top_contracts":[["2SXE",142],["3SE",121],["3DS",58]]}],"dead_options":[]},"difficulty":1.22,"quality":{"n_samples":512,"quality":0.8,"gap_imps":1.22,"ci":0.52,"stakes":4.65,"doubled_share":0.3,"top2":["P","3C"],"q":0.826,"p4":0.435,"tv":1.0,"flip":0.646,"span":false,"trap":false,"damage":true,"interest":92,"p_top_wins":0.402,"p_second_wins":0.424,"winner_by":"EV gap >= 0.5 IMPs","half_stats":[{"gap_imps":0.28,"p_top_wins":0.348,"p_second_wins":0.477},{"gap_imps":2.16,"p_top_wins":0.457,"p_second_wins":0.371}]},"explanations":{"note":"call meanings follow standard 2/1 Game Force","stem":[{"idx":0,"seat":"N","call":"1C","card":{"text":"3+ !C","hcp":[11,21],"minlen":{"C":3,"D":0,"H":0,"S":0}},"text":"1\u2663 (N): 3+\u2663, 11-21"},{"idx":1,"seat":"E","call":"2S","card":{"text":"Weak natural 2M","hcp":[6,10],"minlen":{"C":0,"D":0,"H":0,"S":6}},"text":"2\u2660 (E): Weak natural 2M, 6+\u2660, 6-10"},{"idx":2,"seat":"S","call":"P","card":{"text":"","hcp":[0,13],"minlen":{"C":0,"D":0,"H":0,"S":0}},"text":"Pass (S): 0-13"},{"idx":3,"seat":"W","call":"P","card":{"text":"","hcp":[0,18],"minlen":{"C":0,"D":0,"H":0,"S":0}},"text":"Pass (W): 0-18"}],"options":[{"bid":"P","text":"Pass \u2014 11-21. Leads to 2\u2660E 100%. Engine: 65%. Best: +1.2 IMPs vs 3\u2663 (\u00b10.5), wins 40% of layouts.","card":{"text":"","hcp":[11,21],"minlen":{"C":3,"D":0,"H":0,"S":0}}},{"bid":"3C","text":"3\u2663 \u2014 6+\u2663, 13-17. Leads to 3\u2663N 21%, 4\u2663N 20%, 4\u2660E 14%. Engine: 44%. -1.2 IMPs vs the top choice (\u00b10.5), wins 42%, pushes 17%.","card":{"text":"bidable suit","hcp":[13,17],"minlen":{"C":6,"D":0,"H":0,"S":0}}},{"bid":"X","text":"Dbl \u2014 reopening double, 11-21. Leads to 2SXE 28%, 3\u2660E 24%, 3\u2666S 11%. Engine: 12%. -3.1 IMPs vs the top choice (\u00b10.6), wins 31%, pushes 23%.","card":{"text":"reopening double","hcp":[11,21],"minlen":{"C":3,"D":3,"H":3,"S":0}}}]},"hero_role":"opener","full_deal":{"N":"K.854.962.AKJ952","E":"QJ8652.AJ.T7.643","S":"T974.Q73.AK843.7","W":"A3.KT962.QJ5.QT8"},"engine_auction_complete":["1C","2S","P","P","P"],"policy_trail":[{"idx":0,"seat":"N","chosen":"1C","policy":[["1C",1.197]]},{"idx":1,"seat":"E","chosen":"2S","policy":[["2S",1.073],["1S",0.102]]},{"idx":2,"seat":"S","chosen":"P","policy":[["P",1.17],["3D",0.022]]},{"idx":3,"seat":"W","chosen":"P","policy":[["P",1.195]]},{"idx":4,"seat":"N","chosen":"P","policy":[["P",0.647],["3C",0.436],["X",0.117]]}],"classification":{"difficulty_score":69.0,"difficulty_level":5}}