{"schema":1,"kind":"lead","classification":{"difficulty_level":3},"id":"lead1-000caac2","created_at":"2026-07-18T10:11:48+00:00","generator":{"engine":"ben BEN-21GF","seed":830146,"samples":116,"elapsed_s":9.7},"scoring_form":"tricks","dealer":"E","vul":"Both","declarer":"S","contract":"3HS","leader":"W","seat":"W","hand":"85.JT9.J3.AT8762","auction":["2S","P","P","3C","P","3H","P","P","P"],"candidates":[{"card":"S8","avg_def_tricks":3.009,"ben_softmax":0.537},{"card":"S5","avg_def_tricks":3.009,"ben_softmax":0.043},{"card":"DJ","avg_def_tricks":2.759,"ben_softmax":0.152},{"card":"D3","avg_def_tricks":2.75,"ben_softmax":0.036},{"card":"HJ","avg_def_tricks":2.647,"ben_softmax":0.106},{"card":"HT","avg_def_tricks":2.647,"ben_softmax":0.001},{"card":"H9","avg_def_tricks":2.647,"ben_softmax":0.001},{"card":"CA","avg_def_tricks":2.56,"ben_softmax":0.111},{"card":"C8","avg_def_tricks":2.457,"ben_softmax":0.001},{"card":"C7","avg_def_tricks":2.457,"ben_softmax":0.01},{"card":"C6","avg_def_tricks":2.457,"ben_softmax":0.01},{"card":"C2","avg_def_tricks":2.457,"ben_softmax":0.01},{"card":"CT","avg_def_tricks":2.44,"ben_softmax":0.001}],"verdict":{"accepted":["S8","S5"],"gap":0.25,"n_samples":116,"table":[{"card":"S8","avg_def_tricks":3.009,"vs_best":0.0,"ben_softmax":0.537},{"card":"S5","avg_def_tricks":3.009,"vs_best":0.0,"ben_softmax":0.043},{"card":"DJ","avg_def_tricks":2.759,"vs_best":-0.25,"ben_softmax":0.152},{"card":"D3","avg_def_tricks":2.75,"vs_best":-0.259,"ben_softmax":0.036},{"card":"HJ","avg_def_tricks":2.647,"vs_best":-0.362,"ben_softmax":0.106},{"card":"HT","avg_def_tricks":2.647,"vs_best":-0.362,"ben_softmax":0.001},{"card":"H9","avg_def_tricks":2.647,"vs_best":-0.362,"ben_softmax":0.001},{"card":"CA","avg_def_tricks":2.56,"vs_best":-0.448,"ben_softmax":0.111},{"card":"C8","avg_def_tricks":2.457,"vs_best":-0.552,"ben_softmax":0.001},{"card":"C7","avg_def_tricks":2.457,"vs_best":-0.552,"ben_softmax":0.01},{"card":"C6","avg_def_tricks":2.457,"vs_best":-0.552,"ben_softmax":0.01},{"card":"C2","avg_def_tricks":2.457,"vs_best":-0.552,"ben_softmax":0.01},{"card":"CT","avg_def_tricks":2.44,"vs_best":-0.569,"ben_softmax":0.001}],"flags":[]},"difficulty":3,"quality":{"n_samples":116,"quality":0.74,"best_avg_tricks":3.009,"gap":0.25,"doubled":false,"trap":false,"ben_conf_in_best":0.537,"n_close_suits":4,"top_softmax_card":"S8","top_softmax":0.537,"gap_halves":[0.293,0.19]},"explanations":{"note":"call meanings follow standard 2/1 Game Force","auction":[{"idx":0,"seat":"E","call":"2S","text":"Weak natural 2M, 6+\u2660, 5-10"},{"idx":1,"seat":"S","call":"P","text":"0-16"},{"idx":2,"seat":"W","call":"P","text":"0-16"},{"idx":3,"seat":"N","call":"3C","text":"5+\u2663, 12+"},{"idx":4,"seat":"E","call":"P","text":"6+\u2660, 5-10"},{"idx":5,"seat":"S","call":"3H","text":"5+\u2665, 10-16"},{"idx":6,"seat":"W","call":"P","text":"0-14"},{"idx":7,"seat":"N","call":"P","text":"5+\u2663, 12-14"},{"idx":8,"seat":"E","call":"P","text":"6+\u2660, 5-10"}],"cards":[{"card":"S8","text":"Best lead \u2014 the defense averages 3.01 tricks, more than any other card."},{"card":"S5","text":"Best lead \u2014 the defense averages 3.01 tricks, more than any other card."},{"card":"DJ","text":"Averages 2.76 defensive tricks (-0.25 vs the best lead; rank 3 of 13)."},{"card":"D3","text":"Averages 2.75 defensive tricks (-0.26 vs the best lead; rank 4 of 13)."},{"card":"HJ","text":"Averages 2.65 defensive tricks (-0.36 vs the best lead; rank 5 of 13)."},{"card":"HT","text":"Averages 2.65 defensive tricks (-0.36 vs the best lead; rank 6 of 13)."},{"card":"H9","text":"Averages 2.65 defensive tricks (-0.36 vs the best lead; rank 7 of 13)."},{"card":"CA","text":"Averages 2.56 defensive tricks (-0.45 vs the best lead; rank 8 of 13)."},{"card":"C8","text":"Averages 2.46 defensive tricks (-0.55 vs the best lead; rank 9 of 13)."},{"card":"C7","text":"Averages 2.46 defensive tricks (-0.55 vs the best lead; rank 10 of 13)."},{"card":"C6","text":"Averages 2.46 defensive tricks (-0.55 vs the best lead; rank 11 of 13)."},{"card":"C2","text":"Averages 2.46 defensive tricks (-0.55 vs the best lead; rank 12 of 13)."},{"card":"CT","text":"Averages 2.44 defensive tricks (-0.57 vs the best lead; rank 13 of 13)."}]},"full_deal":{"N":"64.86.AK87.KQJ53","E":"AJ9732.K5.Q652.9","S":"KQT.AQ7432.T94.4","W":"85.JT9.J3.AT8762"},"engine_auction_complete":["2S","P","P","3C","P","3H","P","P","P"]}