{"schema":1,"kind":"lead","classification":{"difficulty_level":3},"id":"lead1-000c3531","created_at":"2026-07-17T23:28:01+00:00","generator":{"engine":"ben BEN-21GF","seed":800049,"samples":151,"elapsed_s":4.5},"scoring_form":"tricks","dealer":"W","vul":"EW","declarer":"E","contract":"4HE","leader":"S","seat":"S","hand":"J92.Q7.732.AKQJ5","auction":["P","P","1H","2C","2NT","P","4C","P","4H","P","P","P"],"candidates":[{"card":"CA","avg_def_tricks":1.159,"ben_softmax":0.459},{"card":"CK","avg_def_tricks":1.159,"ben_softmax":0.401},{"card":"CQ","avg_def_tricks":1.159,"ben_softmax":0.015},{"card":"CJ","avg_def_tricks":1.159,"ben_softmax":0.001},{"card":"D7","avg_def_tricks":0.874,"ben_softmax":0.056},{"card":"D3","avg_def_tricks":0.874,"ben_softmax":0.056},{"card":"D2","avg_def_tricks":0.874,"ben_softmax":0.056},{"card":"H7","avg_def_tricks":0.854,"ben_softmax":0.001},{"card":"S2","avg_def_tricks":0.841,"ben_softmax":0.056},{"card":"SJ","avg_def_tricks":0.834,"ben_softmax":0.001},{"card":"S9","avg_def_tricks":0.834,"ben_softmax":0.004},{"card":"HQ","avg_def_tricks":0.834,"ben_softmax":0.005},{"card":"C5","avg_def_tricks":0.642,"ben_softmax":0.0}],"verdict":{"accepted":["CA","CK","CQ","CJ"],"gap":0.285,"n_samples":151,"table":[{"card":"CA","avg_def_tricks":1.159,"vs_best":0.0,"ben_softmax":0.459},{"card":"CK","avg_def_tricks":1.159,"vs_best":0.0,"ben_softmax":0.401},{"card":"CQ","avg_def_tricks":1.159,"vs_best":0.0,"ben_softmax":0.015},{"card":"CJ","avg_def_tricks":1.159,"vs_best":0.0,"ben_softmax":0.001},{"card":"D7","avg_def_tricks":0.874,"vs_best":-0.285,"ben_softmax":0.056},{"card":"D3","avg_def_tricks":0.874,"vs_best":-0.285,"ben_softmax":0.056},{"card":"D2","avg_def_tricks":0.874,"vs_best":-0.285,"ben_softmax":0.056},{"card":"H7","avg_def_tricks":0.854,"vs_best":-0.305,"ben_softmax":0.001},{"card":"S2","avg_def_tricks":0.841,"vs_best":-0.318,"ben_softmax":0.056},{"card":"SJ","avg_def_tricks":0.834,"vs_best":-0.325,"ben_softmax":0.001},{"card":"S9","avg_def_tricks":0.834,"vs_best":-0.325,"ben_softmax":0.004},{"card":"HQ","avg_def_tricks":0.834,"vs_best":-0.325,"ben_softmax":0.005},{"card":"C5","avg_def_tricks":0.642,"vs_best":-0.517,"ben_softmax":0.0}],"flags":[]},"difficulty":3,"quality":{"n_samples":151,"quality":0.747,"best_avg_tricks":1.159,"gap":0.285,"doubled":false,"trap":false,"ben_conf_in_best":0.459,"n_close_suits":4,"top_softmax_card":"CA","top_softmax":0.459,"gap_halves":[0.253,0.303]},"explanations":{"note":"call meanings follow standard 2/1 Game Force","auction":[{"idx":0,"seat":"W","call":"P","text":"0-11"},{"idx":1,"seat":"N","call":"P","text":"0-11"},{"idx":2,"seat":"E","call":"1H","text":"5+\u2665, 11-20"},{"idx":3,"seat":"S","call":"2C","text":"5+\u2663, 12-17"},{"idx":4,"seat":"W","call":"2NT","text":"10-11"},{"idx":5,"seat":"N","call":"P","text":"0-8"},{"idx":6,"seat":"E","call":"4C","text":"Splinter, 5+\u2665, 13-20"},{"idx":7,"seat":"S","call":"P","text":"5+\u2663, 12-17"},{"idx":8,"seat":"W","call":"4H","text":"3+\u2665, 10-11"},{"idx":9,"seat":"N","call":"P","text":"0-6"},{"idx":10,"seat":"E","call":"P","text":"5+\u2665, 13-16"},{"idx":11,"seat":"S","call":"P","text":"5+\u2663, 12-17"}],"cards":[{"card":"CA","text":"Best lead \u2014 the defense averages 1.16 tricks, more than any other card."},{"card":"CK","text":"Best lead \u2014 the defense averages 1.16 tricks, more than any other card."},{"card":"CQ","text":"Best lead \u2014 the defense averages 1.16 tricks, more than any other card."},{"card":"CJ","text":"Best lead \u2014 the defense averages 1.16 tricks, more than any other card."},{"card":"D7","text":"Averages 0.87 defensive tricks (-0.28 vs the best lead; rank 5 of 13)."},{"card":"D3","text":"Averages 0.87 defensive tricks (-0.28 vs the best lead; rank 6 of 13)."},{"card":"D2","text":"Averages 0.87 defensive tricks (-0.28 vs the best lead; rank 7 of 13)."},{"card":"H7","text":"Averages 0.85 defensive tricks (-0.30 vs the best lead; rank 8 of 13)."},{"card":"S2","text":"Averages 0.84 defensive tricks (-0.32 vs the best lead; rank 9 of 13)."},{"card":"SJ","text":"Averages 0.83 defensive tricks (-0.33 vs the best lead; rank 10 of 13)."},{"card":"S9","text":"Averages 0.83 defensive tricks (-0.33 vs the best lead; rank 11 of 13)."},{"card":"HQ","text":"Averages 0.83 defensive tricks (-0.33 vs the best lead; rank 12 of 13)."},{"card":"C5","text":"Averages 0.64 defensive tricks (-0.52 vs the best lead; rank 13 of 13)."}]},"full_deal":{"N":"753.T54.QJ9.8742","E":"A84.AJ962.AT84.3","S":"J92.Q7.732.AKQJ5","W":"KQT6.K83.K65.T96"},"engine_auction_complete":["P","P","1H","2C","2NT","P","4C","P","4H","P","P","P"]}