{"schema":1,"kind":"lead","classification":{"difficulty_level":3},"id":"lead1-013b29d4","created_at":"2026-07-18T21:45:11+00:00","generator":{"engine":"ben BEN-21GF","seed":20654548,"samples":256,"elapsed_s":7.7},"scoring_form":"tricks","dealer":"W","vul":"Both","declarer":"N","contract":"3NTN","leader":"E","seat":"E","hand":"KJ9.8765.9865.63","auction":["P","1H","P","2C","P","2NT","P","3D","P","3NT","P","P","P"],"candidates":[{"card":"SJ","avg_def_tricks":2.141,"ben_softmax":0.337},{"card":"SK","avg_def_tricks":2.109,"ben_softmax":0.054},{"card":"S9","avg_def_tricks":2.102,"ben_softmax":0.021},{"card":"D9","avg_def_tricks":1.746,"ben_softmax":0.008},{"card":"D8","avg_def_tricks":1.746,"ben_softmax":0.014},{"card":"D6","avg_def_tricks":1.746,"ben_softmax":0.231},{"card":"D5","avg_def_tricks":1.746,"ben_softmax":0.231},{"card":"C6","avg_def_tricks":1.703,"ben_softmax":0.285},{"card":"C3","avg_def_tricks":1.703,"ben_softmax":0.285},{"card":"H8","avg_def_tricks":1.656,"ben_softmax":0.001},{"card":"H7","avg_def_tricks":1.656,"ben_softmax":0.049},{"card":"H6","avg_def_tricks":1.656,"ben_softmax":0.049},{"card":"H5","avg_def_tricks":1.656,"ben_softmax":0.049}],"verdict":{"accepted":["SK","SJ","S9"],"gap":0.395,"n_samples":256,"table":[{"card":"SJ","avg_def_tricks":2.141,"vs_best":0.0,"ben_softmax":0.337},{"card":"SK","avg_def_tricks":2.109,"vs_best":-0.031,"ben_softmax":0.054},{"card":"S9","avg_def_tricks":2.102,"vs_best":-0.039,"ben_softmax":0.021},{"card":"D9","avg_def_tricks":1.746,"vs_best":-0.395,"ben_softmax":0.008},{"card":"D8","avg_def_tricks":1.746,"vs_best":-0.395,"ben_softmax":0.014},{"card":"D6","avg_def_tricks":1.746,"vs_best":-0.395,"ben_softmax":0.231},{"card":"D5","avg_def_tricks":1.746,"vs_best":-0.395,"ben_softmax":0.231},{"card":"C6","avg_def_tricks":1.703,"vs_best":-0.438,"ben_softmax":0.285},{"card":"C3","avg_def_tricks":1.703,"vs_best":-0.438,"ben_softmax":0.285},{"card":"H8","avg_def_tricks":1.656,"vs_best":-0.484,"ben_softmax":0.001},{"card":"H7","avg_def_tricks":1.656,"vs_best":-0.484,"ben_softmax":0.049},{"card":"H6","avg_def_tricks":1.656,"vs_best":-0.484,"ben_softmax":0.049},{"card":"H5","avg_def_tricks":1.656,"vs_best":-0.484,"ben_softmax":0.049}],"flags":[]},"difficulty":3,"quality":{"n_samples":256,"quality":0.803,"best_avg_tricks":2.141,"gap":0.395,"doubled":false,"trap":false,"ben_conf_in_best":0.337,"n_close_suits":4,"top_softmax_card":"SJ","top_softmax":0.337,"gap_halves":[0.438,0.312]},"explanations":{"note":"call meanings follow standard 2/1 Game Force","auction":[{"idx":0,"seat":"W","call":"P","text":"0-11"},{"idx":1,"seat":"N","call":"1H","text":"5+\u2665, 11-20"},{"idx":2,"seat":"E","call":"P","text":"0-14"},{"idx":3,"seat":"S","call":"2C","text":"4+\u2663, 12+"},{"idx":4,"seat":"W","call":"P","text":"0-11"},{"idx":5,"seat":"N","call":"2NT","text":"minimum, 5+\u2665, 11-15"},{"idx":6,"seat":"E","call":"P","text":"0-14"},{"idx":7,"seat":"S","call":"3D","text":"5+\u2663, 4+\u2666, 12+"},{"idx":8,"seat":"W","call":"P","text":"0-11"},{"idx":9,"seat":"N","call":"3NT","text":"5+\u2665, 11-15"},{"idx":10,"seat":"E","call":"P","text":"0-14"},{"idx":11,"seat":"S","call":"P","text":"5+\u2663, 4+\u2666, 12+"},{"idx":12,"seat":"W","call":"P","text":"0-11"}],"cards":[{"card":"SJ","text":"Best lead \u2014 the defense averages 2.14 tricks, more than any other card."},{"card":"SK","text":"Best lead \u2014 the defense averages 2.11 tricks, more than any other card."},{"card":"S9","text":"Best lead \u2014 the defense averages 2.10 tricks, more than any other card."},{"card":"D9","text":"Averages 1.75 defensive tricks (-0.40 vs the best lead; rank 4 of 13)."},{"card":"D8","text":"Averages 1.75 defensive tricks (-0.40 vs the best lead; rank 5 of 13)."},{"card":"D6","text":"Averages 1.75 defensive tricks (-0.40 vs the best lead; rank 6 of 13)."},{"card":"D5","text":"Averages 1.75 defensive tricks (-0.40 vs the best lead; rank 7 of 13)."},{"card":"C6","text":"Averages 1.70 defensive tricks (-0.44 vs the best lead; rank 8 of 13)."},{"card":"C3","text":"Averages 1.70 defensive tricks (-0.44 vs the best lead; rank 9 of 13)."},{"card":"H8","text":"Averages 1.66 defensive tricks (-0.48 vs the best lead; rank 10 of 13)."},{"card":"H7","text":"Averages 1.66 defensive tricks (-0.48 vs the best lead; rank 11 of 13)."},{"card":"H6","text":"Averages 1.66 defensive tricks (-0.48 vs the best lead; rank 12 of 13)."},{"card":"H5","text":"Averages 1.66 defensive tricks (-0.48 vs the best lead; rank 13 of 13)."}]},"full_deal":{"N":"QT83.AKQT3.QJ.T5","E":"KJ9.8765.9865.63","S":"A74.2.AT32.KQ872","W":"652.J94.K74.AJ94"},"engine_auction_complete":["P","1H","P","2C","P","2NT","P","3D","P","3NT","P","P","P"]}