{"schema":1,"kind":"lead","classification":{"difficulty_level":1},"id":"lead1-013b28eb","created_at":"2026-07-18T21:27:41+00:00","generator":{"engine":"ben BEN-21GF","seed":20654315,"samples":245,"elapsed_s":9.8},"scoring_form":"tricks","dealer":"W","vul":"NS","declarer":"W","contract":"4HW","leader":"N","seat":"N","hand":"AKT82.Q72.52.842","auction":["2NT","P","3D","P","3H","P","3NT","P","4H","P","P","P"],"candidates":[{"card":"SA","avg_def_tricks":2.633,"ben_softmax":0.031},{"card":"SK","avg_def_tricks":2.633,"ben_softmax":0.509},{"card":"D5","avg_def_tricks":1.992,"ben_softmax":0.261},{"card":"D2","avg_def_tricks":1.992,"ben_softmax":0.261},{"card":"C8","avg_def_tricks":1.967,"ben_softmax":0.003},{"card":"C4","avg_def_tricks":1.967,"ben_softmax":0.173},{"card":"C2","avg_def_tricks":1.967,"ben_softmax":0.173},{"card":"ST","avg_def_tricks":1.686,"ben_softmax":0.0},{"card":"S8","avg_def_tricks":1.682,"ben_softmax":0.0},{"card":"S2","avg_def_tricks":1.682,"ben_softmax":0.001},{"card":"H7","avg_def_tricks":1.465,"ben_softmax":0.023},{"card":"H2","avg_def_tricks":1.465,"ben_softmax":0.023},{"card":"HQ","avg_def_tricks":1.269,"ben_softmax":0.001}],"verdict":{"accepted":["SA","SK"],"gap":0.641,"n_samples":245,"table":[{"card":"SA","avg_def_tricks":2.633,"vs_best":0.0,"ben_softmax":0.031},{"card":"SK","avg_def_tricks":2.633,"vs_best":0.0,"ben_softmax":0.509},{"card":"D5","avg_def_tricks":1.992,"vs_best":-0.641,"ben_softmax":0.261},{"card":"D2","avg_def_tricks":1.992,"vs_best":-0.641,"ben_softmax":0.261},{"card":"C8","avg_def_tricks":1.967,"vs_best":-0.665,"ben_softmax":0.003},{"card":"C4","avg_def_tricks":1.967,"vs_best":-0.665,"ben_softmax":0.173},{"card":"C2","avg_def_tricks":1.967,"vs_best":-0.665,"ben_softmax":0.173},{"card":"ST","avg_def_tricks":1.686,"vs_best":-0.947,"ben_softmax":0.0},{"card":"S8","avg_def_tricks":1.682,"vs_best":-0.951,"ben_softmax":0.0},{"card":"S2","avg_def_tricks":1.682,"vs_best":-0.951,"ben_softmax":0.001},{"card":"H7","avg_def_tricks":1.465,"vs_best":-1.167,"ben_softmax":0.023},{"card":"H2","avg_def_tricks":1.465,"vs_best":-1.167,"ben_softmax":0.023},{"card":"HQ","avg_def_tricks":1.269,"vs_best":-1.363,"ben_softmax":0.001}],"flags":[]},"difficulty":1,"quality":{"n_samples":245,"quality":0.813,"best_avg_tricks":2.633,"gap":0.641,"doubled":false,"trap":false,"ben_conf_in_best":0.509,"n_close_suits":1,"top_softmax_card":"SK","top_softmax":0.509,"gap_halves":[0.631,0.65]},"explanations":{"note":"call meanings follow standard 2/1 Game Force","auction":[{"idx":0,"seat":"W","call":"2NT","text":"NT style, 20-21"},{"idx":1,"seat":"N","call":"P","text":"0-17"},{"idx":2,"seat":"E","call":"3D","text":"transfer, 5+\u2665, 0-20"},{"idx":3,"seat":"S","call":"P","text":"0-18"},{"idx":4,"seat":"W","call":"3H","text":"transfer completed, 20-21"},{"idx":5,"seat":"N","call":"P","text":"0-17"},{"idx":6,"seat":"E","call":"3NT","text":"5+\u2665, 4-10"},{"idx":7,"seat":"S","call":"P","text":"0-17"},{"idx":8,"seat":"W","call":"4H","text":"3+\u2665, 20-21"},{"idx":9,"seat":"N","call":"P","text":"0-17"},{"idx":10,"seat":"E","call":"P","text":"5+\u2665, 4-6"},{"idx":11,"seat":"S","call":"P","text":"0-17"}],"cards":[{"card":"SA","text":"Best lead \u2014 the defense averages 2.63 tricks, more than any other card."},{"card":"SK","text":"Best lead \u2014 the defense averages 2.63 tricks, more than any other card."},{"card":"D5","text":"Averages 1.99 defensive tricks (-0.64 vs the best lead; rank 3 of 13)."},{"card":"D2","text":"Averages 1.99 defensive tricks (-0.64 vs the best lead; rank 4 of 13)."},{"card":"C8","text":"Averages 1.97 defensive tricks (-0.67 vs the best lead; rank 5 of 13)."},{"card":"C4","text":"Averages 1.97 defensive tricks (-0.67 vs the best lead; rank 6 of 13)."},{"card":"C2","text":"Averages 1.97 defensive tricks (-0.67 vs the best lead; rank 7 of 13)."},{"card":"ST","text":"Averages 1.69 defensive tricks (-0.95 vs the best lead; rank 8 of 13)."},{"card":"S8","text":"Averages 1.68 defensive tricks (-0.95 vs the best lead; rank 9 of 13)."},{"card":"S2","text":"Averages 1.68 defensive tricks (-0.95 vs the best lead; rank 10 of 13)."},{"card":"H7","text":"Averages 1.47 defensive tricks (-1.17 vs the best lead; rank 11 of 13)."},{"card":"H2","text":"Averages 1.47 defensive tricks (-1.17 vs the best lead; rank 12 of 13)."},{"card":"HQ","text":"Averages 1.27 defensive tricks (-1.36 vs the best lead; rank 13 of 13)."}]},"full_deal":{"N":"AKT82.Q72.52.842","E":"Q.JT643.Q943.J97","S":"9753.95.KT876.Q6","W":"J64.AK8.AJ.AKT53"},"engine_auction_complete":["2NT","P","3D","P","3H","P","3NT","P","4H","P","P","P"]}