{
 "50011-14": {
  "dealer": "E",
  "vul": "None",
  "hero": "S",
  "hero_hand": "954.AKT976.AQ7.5",
  "stem": [
   "P",
   "1H",
   "P",
   "1S",
   "P",
   "2H",
   "P",
   "3C",
   "P"
  ],
  "room_calls_at_decision": {
   "o": "3S",
   "c": "3NT"
  }
 },
 "50007-23": {
  "dealer": "S",
  "vul": "Both",
  "hero": "S",
  "hero_hand": "KT962.6.AK75.Q87",
  "stem": [
   "1S",
   "P",
   "2C",
   "P",
   "2D",
   "P",
   "3D",
   "P"
  ],
  "room_calls_at_decision": {
   "o": "3H",
   "c": "3S"
  }
 },
 "50015-7": {
  "dealer": "S",
  "vul": "Both",
  "hero": "S",
  "hero_hand": "T8542.T986.AQ4.6",
  "stem": [
   "P",
   "P",
   "1NT",
   "P",
   "2C",
   "P",
   "2H",
   "P"
  ],
  "room_calls_at_decision": {
   "o": "3H",
   "c": "4H"
  }
 },
 "50000-8": {
  "dealer": "W",
  "vul": "None",
  "hero": "S",
  "hero_hand": "Q42.KJT86.T82.T3",
  "stem": [
   "P",
   "1NT",
   "P",
   "2D",
   "X",
   "P",
   "P"
  ],
  "room_calls_at_decision": {
   "o": "2H",
   "c": "XX"
  }
 },
 "50003-32": {
  "dealer": "W",
  "vul": "EW",
  "hero": "E",
  "hero_hand": "Q85.AKQJ3.A9.A82",
  "stem": [
   "P",
   "P",
   "2NT",
   "P",
   "3C",
   "P"
  ],
  "room_calls_at_decision": {
   "o": "3NT",
   "c": "3H"
  }
 },
 "50007-31": {
  "dealer": "S",
  "vul": "NS",
  "hero": "N",
  "hero_hand": "AJ943.Q85.93.Q64",
  "stem": [
   "1C",
   "P",
   "1S",
   "P",
   "1NT",
   "P"
  ],
  "room_calls_at_decision": {
   "o": "P",
   "c": "2S"
  }
 },
 "50024-25": {
  "dealer": "N",
  "vul": "EW",
  "hero": "S",
  "hero_hand": "J2.K632.AK62.973",
  "stem": [
   "1S",
   "P",
   "1NT",
   "P",
   "2H",
   "P"
  ],
  "room_calls_at_decision": {
   "o": "3H",
   "c": "4H"
  }
 },
 "50006-27": {
  "dealer": "S",
  "vul": "None",
  "hero": "W",
  "hero_hand": "AJT9.9.AQJ762.64",
  "stem": [
   "2S",
   "3D",
   "P",
   "4C",
   "P"
  ],
  "room_calls_at_decision": {
   "o": "4D",
   "c": "4S"
  }
 },
 "50000-7": {
  "dealer": "S",
  "vul": "Both",
  "hero": "W",
  "hero_hand": "975.A973.K543.A6",
  "stem": [
   "P"
  ],
  "room_calls_at_decision": {
   "o": "P",
   "c": "1D"
  }
 },
 "50000-13": {
  "dealer": "N",
  "vul": "Both",
  "hero": "E",
  "hero_hand": "AK5.KJ2.AQ42.KQ7",
  "stem": [
   "P"
  ],
  "room_calls_at_decision": {
   "o": "2NT",
   "c": "2D"
  }
 },
 "50006-19": {
  "dealer": "S",
  "vul": "EW",
  "hero": "W",
  "hero_hand": "AK98.A865.K64.K2",
  "stem": [
   "P"
  ],
  "room_calls_at_decision": {
   "o": "1D",
   "c": "1NT"
  }
 },
 "50012-16": {
  "dealer": "W",
  "vul": "EW",
  "hero": "N",
  "hero_hand": "T84.AT2.KJT5.A72",
  "stem": [
   "P"
  ],
  "room_calls_at_decision": {
   "o": "1D",
   "c": "1NT"
  }
 },
 "50020-17": {
  "dealer": "N",
  "vul": "None",
  "hero": "E",
  "hero_hand": "3.J5.KQT84.QJ943",
  "stem": [
   "1S"
  ],
  "room_calls_at_decision": {
   "o": "P",
   "c": "2NT"
  }
 },
 "50007-22": {
  "dealer": "E",
  "vul": "EW",
  "hero": "W",
  "hero_hand": "T7.AJT952.J.6432",
  "stem": [
   "1C",
   "1NT"
  ],
  "room_calls_at_decision": {
   "o": "2D",
   "c": "P"
  }
 },
 "50011-12": {
  "dealer": "W",
  "vul": "NS",
  "hero": "E",
  "hero_hand": "J832.A97.A84.Q72",
  "stem": [
   "1S",
   "P"
  ],
  "room_calls_at_decision": {
   "o": "3H",
   "c": "3S"
  }
 },
 "50012-6": {
  "dealer": "E",
  "vul": "EW",
  "hero": "W",
  "hero_hand": "T98.9653.JT2.964",
  "stem": [
   "1NT",
   "P"
  ],
  "room_calls_at_decision": {
   "o": "P",
   "c": "2C"
  }
 }
}